[
  {
    "@context": [
      "https://uri.etsi.org/ngsi-ld/v1/ngsi-ld-core-context.jsonld"
    ],
    "id": "urn:ngsi-ld:TwinObject:AutoEquipment:361-900A",
    "type": "TwinObject",
    "name": {
      "type": "Property",
      "value": "焊接机械手"
    },
    "twinType": {
      "type": "Property",
      "value": "Constituent"
    },
    "subType": {
      "type": "Property",
      "value": "AutoEquipment"
    },
    "functionCategory": {
      "type": "Property",
      "value": "F1.2.1"
    },
    "deviceType": {
      "type": "Property",
      "value": "Robot"
    },
    "vendor": {
      "type": "Property",
      "value": "德国克鲁斯焊接技术公司"
    },
    "model": {
      "type": "Property",
      "value": "R350"
    },
    "serialNumber": {
      "type": "Property",
      "value": "300696"
    },
    "assetNumber": {
      "type": "Property",
      "value": "361-900A"
    },
    "operationalStatus": {
      "type": "Property",
      "value": "在用"
    },
    "powerRating": {
      "type": "Property",
      "value": 60.0,
      "unitCode": "kW"
    },
    "weight": {
      "type": "Property",
      "value": 20000.0,
      "unitCode": "kg"
    },
    "dimensions": {
      "type": "Property",
      "value": {
        "length_mm": 3500.0,
        "width_mm": 1650.0,
        "height_mm": 2500.0
      }
    },
    "manufactureDate": {
      "type": "Property",
      "value": "2004-03-01"
    },
    "installationDate": {
      "type": "Property",
      "value": "2004-09-27"
    },
    "lastMaintenanceDate": {
      "type": "Property",
      "value": "2020-08-07"
    },
    "nextMaintenanceDate": {
      "type": "Property",
      "value": "2020-05-26"
    },
    "location": {
      "type": "Property",
      "value": "侧墙组焊工位 (TS36120201)"
    },
    "axes": {
      "type": "Property",
      "value": 6,
      "unitCode": "axes"
    },
    "reach": {
      "type": "Property",
      "value": 2650,
      "unitCode": "mm"
    },
    "payload": {
      "type": "Property",
      "value": 210,
      "unitCode": "kg"
    },
    "repeatability": {
      "type": "Property",
      "value": 0.08,
      "unitCode": "mm"
    },
    "safetyFeatures": {
      "type": "Property",
      "value": [
        "EmergencyStop",
        "SafetyZone",
        "CollisionDetection"
      ]
    },
    "materialCode": {
      "type": "Property",
      "value": "1700000096"
    }
  },
  {
    "@context": [
      "https://uri.etsi.org/ngsi-ld/v1/ngsi-ld-core-context.jsonld"
    ],
    "id": "urn:ngsi-ld:TwinObject:AutoEquipment:361-01156",
    "type": "TwinObject",
    "name": {
      "type": "Property",
      "value": "电弧焊接机"
    },
    "twinType": {
      "type": "Property",
      "value": "Constituent"
    },
    "subType": {
      "type": "Property",
      "value": "AutoEquipment"
    },
    "functionCategory": {
      "type": "Property",
      "value": "F1.2.1"
    },
    "deviceType": {
      "type": "Property",
      "value": "Welder"
    },
    "vendor": {
      "type": "Property",
      "value": "珠海市福尼斯焊接技术有限公司"
    },
    "model": {
      "type": "Property",
      "value": "TPS5000"
    },
    "serialNumber": {
      "type": "Property",
      "value": "18140123"
    },
    "assetNumber": {
      "type": "Property",
      "value": "361-01156"
    },
    "operationalStatus": {
      "type": "Property",
      "value": "在用"
    },
    "powerRating": {
      "type": "Property",
      "value": 14.0,
      "unitCode": "kW"
    },
    "weight": {
      "type": "Property",
      "value": 35.0,
      "unitCode": "kg"
    },
    "dimensions": {
      "type": "Property",
      "value": {
        "length_mm": 620.0,
        "width_mm": 300.0,
        "height_mm": 700.0
      }
    },
    "manufactureDate": {
      "type": "Property",
      "value": "2007-05-01"
    },
    "installationDate": {
      "type": "Property",
      "value": "2006-09-30"
    },
    "lastMaintenanceDate": {
      "type": "Property",
      "value": "2025-09-04"
    },
    "nextMaintenanceDate": {
      "type": "Property",
      "value": "2026-01-04"
    },
    "location": {
      "type": "Property",
      "value": "侧墙组焊工位 (TS36120201)"
    },
    "currentRange": {
      "type": "Property",
      "value": {
        "min": 50,
        "max": 500,
        "unit": "A"
      }
    },
    "weldingProcessTypes": {
      "type": "Property",
      "value": [
        "MIG",
        "MAG"
      ]
    },
    "materialCode": {
      "type": "Property",
      "value": "1700000104"
    }
  },
  {
    "@context": [
      "https://uri.etsi.org/ngsi-ld/v1/ngsi-ld-core-context.jsonld"
    ],
    "id": "urn:ngsi-ld:TwinObject:AutoEquipment:361-01341",
    "type": "TwinObject",
    "name": {
      "type": "Property",
      "value": "电弧焊接机"
    },
    "twinType": {
      "type": "Property",
      "value": "Constituent"
    },
    "subType": {
      "type": "Property",
      "value": "AutoEquipment"
    },
    "functionCategory": {
      "type": "Property",
      "value": "F1.2.1"
    },
    "deviceType": {
      "type": "Property",
      "value": "Welder"
    },
    "vendor": {
      "type": "Property",
      "value": "珠海市福尼斯焊接技术有限公司"
    },
    "model": {
      "type": "Property",
      "value": "TPS5000"
    },
    "serialNumber": {
      "type": "Property",
      "value": "20360572"
    },
    "assetNumber": {
      "type": "Property",
      "value": "361-01341"
    },
    "operationalStatus": {
      "type": "Property",
      "value": "在用"
    },
    "powerRating": {
      "type": "Property",
      "value": 14.0,
      "unitCode": "kW"
    },
    "weight": {
      "type": "Property",
      "value": 35.2,
      "unitCode": "kg"
    },
    "dimensions": {
      "type": "Property",
      "value": {
        "length_mm": 626.0,
        "width_mm": 287.0,
        "height_mm": 477.0
      }
    },
    "manufactureDate": {
      "type": "Property",
      "value": "2009-11-01"
    },
    "installationDate": {
      "type": "Property",
      "value": "2009-02-23"
    },
    "lastMaintenanceDate": {
      "type": "Property",
      "value": "2025-07-09"
    },
    "nextMaintenanceDate": {
      "type": "Property",
      "value": "2025-10-25"
    },
    "location": {
      "type": "Property",
      "value": "侧墙组焊工位 (TS36120201)"
    },
    "currentRange": {
      "type": "Property",
      "value": {
        "min": 50,
        "max": 500,
        "unit": "A"
      }
    },
    "weldingProcessTypes": {
      "type": "Property",
      "value": [
        "MIG",
        "MAG"
      ]
    },
    "materialCode": {
      "type": "Property",
      "value": "1700000104"
    }
  },
  {
    "@context": [
      "https://uri.etsi.org/ngsi-ld/v1/ngsi-ld-core-context.jsonld"
    ],
    "id": "urn:ngsi-ld:TwinObject:AutoEquipment:361-899",
    "type": "TwinObject",
    "name": {
      "type": "Property",
      "value": "电弧焊接专机"
    },
    "twinType": {
      "type": "Property",
      "value": "Constituent"
    },
    "subType": {
      "type": "Property",
      "value": "AutoEquipment"
    },
    "functionCategory": {
      "type": "Property",
      "value": "F1.2.1"
    },
    "deviceType": {
      "type": "Property",
      "value": "Other"
    },
    "vendor": {
      "type": "Property",
      "value": "奥地利IGM公司"
    },
    "model": {
      "type": "Property",
      "value": "RTI-2000"
    },
    "serialNumber": {
      "type": "Property",
      "value": "100565/300113"
    },
    "assetNumber": {
      "type": "Property",
      "value": "361-899"
    },
    "operationalStatus": {
      "type": "Property",
      "value": "在用"
    },
    "powerRating": {
      "type": "Property",
      "value": 60.0,
      "unitCode": "kW"
    },
    "weight": {
      "type": "Property",
      "value": 27400.0,
      "unitCode": "kg"
    },
    "dimensions": {
      "type": "Property",
      "value": {
        "length_mm": 50000.0,
        "width_mm": 9000.0,
        "height_mm": 5000.0
      }
    },
    "manufactureDate": {
      "type": "Property",
      "value": "2004-06-01"
    },
    "installationDate": {
      "type": "Property",
      "value": "2004-03-29"
    },
    "lastMaintenanceDate": {
      "type": "Property",
      "value": "2021-11-23"
    },
    "nextMaintenanceDate": {
      "type": "Property",
      "value": "2022-02-01"
    },
    "location": {
      "type": "Property",
      "value": "侧墙组焊工位 (TS36120201)"
    },
    "materialCode": {
      "type": "Property",
      "value": "1700000100"
    }
  },
  {
    "@context": [
      "https://uri.etsi.org/ngsi-ld/v1/ngsi-ld-core-context.jsonld"
    ],
    "id": "urn:ngsi-ld:TwinObject:AutoEquipment:269-00066",
    "type": "TwinObject",
    "name": {
      "type": "Property",
      "value": "焊接机械手"
    },
    "twinType": {
      "type": "Property",
      "value": "Constituent"
    },
    "subType": {
      "type": "Property",
      "value": "AutoEquipment"
    },
    "functionCategory": {
      "type": "Property",
      "value": "F1.2.1"
    },
    "deviceType": {
      "type": "Property",
      "value": "Robot"
    },
    "vendor": {
      "type": "Property",
      "value": "北京艾捷默机器人系统有限公司"
    },
    "model": {
      "type": "Property",
      "value": "RTE 476-S"
    },
    "assetNumber": {
      "type": "Property",
      "value": "269-00066"
    },
    "operationalStatus": {
      "type": "Property",
      "value": "在用"
    },
    "weight": {
      "type": "Property",
      "value": 15500.0,
      "unitCode": "kg"
    },
    "dimensions": {
      "type": "Property",
      "value": {
        "length_mm": 6000.0,
        "width_mm": 12200.0,
        "height_mm": 5600.0
      }
    },
    "manufactureDate": {
      "type": "Property",
      "value": "2019-07-01"
    },
    "installationDate": {
      "type": "Property",
      "value": "2019-07-11"
    },
    "lastMaintenanceDate": {
      "type": "Property",
      "value": "2025-10-20"
    },
    "nextMaintenanceDate": {
      "type": "Property",
      "value": "2026-01-20"
    },
    "location": {
      "type": "Property",
      "value": "侧墙组焊工位 (TS36120201)"
    },
    "axes": {
      "type": "Property",
      "value": 6,
      "unitCode": "axes"
    },
    "safetyFeatures": {
      "type": "Property",
      "value": [
        "EmergencyStop",
        "SafetyZone",
        "CollisionDetection"
      ]
    },
    "materialCode": {
      "type": "Property",
      "value": "1700001358"
    }
  },
  {
    "@context": [
      "https://uri.etsi.org/ngsi-ld/v1/ngsi-ld-core-context.jsonld"
    ],
    "id": "urn:ngsi-ld:TwinObject:AutoEquipment:269-00067",
    "type": "TwinObject",
    "name": {
      "type": "Property",
      "value": "焊接机械手"
    },
    "twinType": {
      "type": "Property",
      "value": "Constituent"
    },
    "subType": {
      "type": "Property",
      "value": "AutoEquipment"
    },
    "functionCategory": {
      "type": "Property",
      "value": "F1.2.1"
    },
    "deviceType": {
      "type": "Property",
      "value": "Robot"
    },
    "vendor": {
      "type": "Property",
      "value": "北京艾捷默机器人系统有限公司"
    },
    "model": {
      "type": "Property",
      "value": "RTE 476-S"
    },
    "assetNumber": {
      "type": "Property",
      "value": "269-00067"
    },
    "operationalStatus": {
      "type": "Property",
      "value": "在用"
    },
    "weight": {
      "type": "Property",
      "value": 15500.0,
      "unitCode": "kg"
    },
    "dimensions": {
      "type": "Property",
      "value": {
        "length_mm": 6000.0,
        "width_mm": 12200.0,
        "height_mm": 5600.0
      }
    },
    "manufactureDate": {
      "type": "Property",
      "value": "2019-07-01"
    },
    "installationDate": {
      "type": "Property",
      "value": "2019-07-11"
    },
    "lastMaintenanceDate": {
      "type": "Property",
      "value": "2025-10-20"
    },
    "nextMaintenanceDate": {
      "type": "Property",
      "value": "2026-01-20"
    },
    "location": {
      "type": "Property",
      "value": "侧墙组焊工位 (TS36120201)"
    },
    "axes": {
      "type": "Property",
      "value": 6,
      "unitCode": "axes"
    },
    "safetyFeatures": {
      "type": "Property",
      "value": [
        "EmergencyStop",
        "SafetyZone",
        "CollisionDetection"
      ]
    },
    "materialCode": {
      "type": "Property",
      "value": "1700001358"
    }
  },
  {
    "@context": [
      "https://uri.etsi.org/ngsi-ld/v1/ngsi-ld-core-context.jsonld"
    ],
    "id": "urn:ngsi-ld:TwinObject:AutoEquipment:361-01144",
    "type": "TwinObject",
    "name": {
      "type": "Property",
      "value": "电弧焊接机"
    },
    "twinType": {
      "type": "Property",
      "value": "Constituent"
    },
    "subType": {
      "type": "Property",
      "value": "AutoEquipment"
    },
    "functionCategory": {
      "type": "Property",
      "value": "F1.2.1"
    },
    "deviceType": {
      "type": "Property",
      "value": "Welder"
    },
    "vendor": {
      "type": "Property",
      "value": "珠海市福尼斯焊接技术有限公司"
    },
    "model": {
      "type": "Property",
      "value": "TPS4000"
    },
    "serialNumber": {
      "type": "Property",
      "value": "18130367"
    },
    "assetNumber": {
      "type": "Property",
      "value": "361-01144"
    },
    "operationalStatus": {
      "type": "Property",
      "value": "在用"
    },
    "powerRating": {
      "type": "Property",
      "value": 14.0,
      "unitCode": "kW"
    },
    "weight": {
      "type": "Property",
      "value": 35.0,
      "unitCode": "kg"
    },
    "dimensions": {
      "type": "Property",
      "value": {
        "length_mm": 620.0,
        "width_mm": 300.0,
        "height_mm": 700.0
      }
    },
    "manufactureDate": {
      "type": "Property",
      "value": "2007-05-01"
    },
    "installationDate": {
      "type": "Property",
      "value": "2006-09-30"
    },
    "lastMaintenanceDate": {
      "type": "Property",
      "value": "2025-09-10"
    },
    "nextMaintenanceDate": {
      "type": "Property",
      "value": "2026-01-10"
    },
    "location": {
      "type": "Property",
      "value": "侧墙组焊工位 (TS36120201)"
    },
    "currentRange": {
      "type": "Property",
      "value": {
        "min": 30,
        "max": 300,
        "unit": "A"
      }
    },
    "weldingProcessTypes": {
      "type": "Property",
      "value": [
        "MIG",
        "MAG"
      ]
    },
    "materialCode": {
      "type": "Property",
      "value": "1700000103"
    }
  },
  {
    "@context": [
      "https://uri.etsi.org/ngsi-ld/v1/ngsi-ld-core-context.jsonld"
    ],
    "id": "urn:ngsi-ld:TwinObject:AutoEquipment:361-01173",
    "type": "TwinObject",
    "name": {
      "type": "Property",
      "value": "电弧焊接机"
    },
    "twinType": {
      "type": "Property",
      "value": "Constituent"
    },
    "subType": {
      "type": "Property",
      "value": "AutoEquipment"
    },
    "functionCategory": {
      "type": "Property",
      "value": "F1.2.1"
    },
    "deviceType": {
      "type": "Property",
      "value": "Welder"
    },
    "vendor": {
      "type": "Property",
      "value": "珠海市福尼斯焊接技术有限公司"
    },
    "model": {
      "type": "Property",
      "value": "TPS4000"
    },
    "serialNumber": {
      "type": "Property",
      "value": "18130376"
    },
    "assetNumber": {
      "type": "Property",
      "value": "361-01173"
    },
    "operationalStatus": {
      "type": "Property",
      "value": "在用"
    },
    "powerRating": {
      "type": "Property",
      "value": 14.0,
      "unitCode": "kW"
    },
    "weight": {
      "type": "Property",
      "value": 35.0,
      "unitCode": "kg"
    },
    "dimensions": {
      "type": "Property",
      "value": {
        "length_mm": 620.0,
        "width_mm": 300.0,
        "height_mm": 700.0
      }
    },
    "manufactureDate": {
      "type": "Property",
      "value": "2007-05-01"
    },
    "installationDate": {
      "type": "Property",
      "value": "2006-09-30"
    },
    "lastMaintenanceDate": {
      "type": "Property",
      "value": "2025-07-09"
    },
    "nextMaintenanceDate": {
      "type": "Property",
      "value": "2025-11-09"
    },
    "location": {
      "type": "Property",
      "value": "侧墙组焊工位 (TS36120201)"
    },
    "currentRange": {
      "type": "Property",
      "value": {
        "min": 30,
        "max": 300,
        "unit": "A"
      }
    },
    "weldingProcessTypes": {
      "type": "Property",
      "value": [
        "MIG",
        "MAG"
      ]
    },
    "materialCode": {
      "type": "Property",
      "value": "1700000103"
    }
  },
  {
    "@context": [
      "https://uri.etsi.org/ngsi-ld/v1/ngsi-ld-core-context.jsonld"
    ],
    "id": "urn:ngsi-ld:TwinObject:AutoEquipment:361-01179",
    "type": "TwinObject",
    "name": {
      "type": "Property",
      "value": "电弧焊接机"
    },
    "twinType": {
      "type": "Property",
      "value": "Constituent"
    },
    "subType": {
      "type": "Property",
      "value": "AutoEquipment"
    },
    "functionCategory": {
      "type": "Property",
      "value": "F1.2.1"
    },
    "deviceType": {
      "type": "Property",
      "value": "Welder"
    },
    "vendor": {
      "type": "Property",
      "value": "珠海市福尼斯焊接技术有限公司"
    },
    "model": {
      "type": "Property",
      "value": "TPS4000"
    },
    "serialNumber": {
      "type": "Property",
      "value": "18130432"
    },
    "assetNumber": {
      "type": "Property",
      "value": "361-01179"
    },
    "operationalStatus": {
      "type": "Property",
      "value": "在用"
    },
    "powerRating": {
      "type": "Property",
      "value": 14.0,
      "unitCode": "kW"
    },
    "weight": {
      "type": "Property",
      "value": 35.0,
      "unitCode": "kg"
    },
    "dimensions": {
      "type": "Property",
      "value": {
        "length_mm": 620.0,
        "width_mm": 300.0,
        "height_mm": 700.0
      }
    },
    "manufactureDate": {
      "type": "Property",
      "value": "2007-05-01"
    },
    "installationDate": {
      "type": "Property",
      "value": "2006-09-30"
    },
    "lastMaintenanceDate": {
      "type": "Property",
      "value": "2025-09-25"
    },
    "nextMaintenanceDate": {
      "type": "Property",
      "value": "2026-01-21"
    },
    "location": {
      "type": "Property",
      "value": "侧墙组焊工位 (TS36120201)"
    },
    "currentRange": {
      "type": "Property",
      "value": {
        "min": 30,
        "max": 300,
        "unit": "A"
      }
    },
    "weldingProcessTypes": {
      "type": "Property",
      "value": [
        "MIG",
        "MAG"
      ]
    },
    "materialCode": {
      "type": "Property",
      "value": "1700000103"
    }
  },
  {
    "@context": [
      "https://uri.etsi.org/ngsi-ld/v1/ngsi-ld-core-context.jsonld"
    ],
    "id": "urn:ngsi-ld:TwinObject:AutoEquipment:361-01184",
    "type": "TwinObject",
    "name": {
      "type": "Property",
      "value": "电弧焊接机"
    },
    "twinType": {
      "type": "Property",
      "value": "Constituent"
    },
    "subType": {
      "type": "Property",
      "value": "AutoEquipment"
    },
    "functionCategory": {
      "type": "Property",
      "value": "F1.2.1"
    },
    "deviceType": {
      "type": "Property",
      "value": "Welder"
    },
    "vendor": {
      "type": "Property",
      "value": "珠海市福尼斯焊接技术有限公司"
    },
    "model": {
      "type": "Property",
      "value": "TPS4000"
    },
    "serialNumber": {
      "type": "Property",
      "value": "18130442"
    },
    "assetNumber": {
      "type": "Property",
      "value": "361-01184"
    },
    "operationalStatus": {
      "type": "Property",
      "value": "在用"
    },
    "powerRating": {
      "type": "Property",
      "value": 14.0,
      "unitCode": "kW"
    },
    "weight": {
      "type": "Property",
      "value": 35.0,
      "unitCode": "kg"
    },
    "dimensions": {
      "type": "Property",
      "value": {
        "length_mm": 620.0,
        "width_mm": 300.0,
        "height_mm": 700.0
      }
    },
    "manufactureDate": {
      "type": "Property",
      "value": "2007-05-01"
    },
    "installationDate": {
      "type": "Property",
      "value": "2006-01-27"
    },
    "lastMaintenanceDate": {
      "type": "Property",
      "value": "2025-07-02"
    },
    "nextMaintenanceDate": {
      "type": "Property",
      "value": "2025-10-25"
    },
    "location": {
      "type": "Property",
      "value": "侧墙组焊工位 (TS36120201)"
    },
    "currentRange": {
      "type": "Property",
      "value": {
        "min": 30,
        "max": 300,
        "unit": "A"
      }
    },
    "weldingProcessTypes": {
      "type": "Property",
      "value": [
        "MIG",
        "MAG"
      ]
    },
    "materialCode": {
      "type": "Property",
      "value": "1700000103"
    }
  },
  {
    "@context": [
      "https://uri.etsi.org/ngsi-ld/v1/ngsi-ld-core-context.jsonld"
    ],
    "id": "urn:ngsi-ld:TwinObject:AutoEquipment:361-01370",
    "type": "TwinObject",
    "name": {
      "type": "Property",
      "value": "电弧焊接机"
    },
    "twinType": {
      "type": "Property",
      "value": "Constituent"
    },
    "subType": {
      "type": "Property",
      "value": "AutoEquipment"
    },
    "functionCategory": {
      "type": "Property",
      "value": "F1.2.1"
    },
    "deviceType": {
      "type": "Property",
      "value": "Welder"
    },
    "vendor": {
      "type": "Property",
      "value": "珠海市福尼斯焊接技术有限公司"
    },
    "model": {
      "type": "Property",
      "value": "TPS4000"
    },
    "serialNumber": {
      "type": "Property",
      "value": "20352671"
    },
    "assetNumber": {
      "type": "Property",
      "value": "361-01370"
    },
    "operationalStatus": {
      "type": "Property",
      "value": "在用"
    },
    "powerRating": {
      "type": "Property",
      "value": 14.0,
      "unitCode": "kW"
    },
    "weight": {
      "type": "Property",
      "value": 35.2,
      "unitCode": "kg"
    },
    "dimensions": {
      "type": "Property",
      "value": {
        "length_mm": 626.0,
        "width_mm": 287.0,
        "height_mm": 477.0
      }
    },
    "manufactureDate": {
      "type": "Property",
      "value": "2009-11-01"
    },
    "installationDate": {
      "type": "Property",
      "value": "2009-02-23"
    },
    "lastMaintenanceDate": {
      "type": "Property",
      "value": "2025-07-02"
    },
    "nextMaintenanceDate": {
      "type": "Property",
      "value": "2025-11-01"
    },
    "location": {
      "type": "Property",
      "value": "侧墙组焊工位 (TS36120201)"
    },
    "currentRange": {
      "type": "Property",
      "value": {
        "min": 30,
        "max": 300,
        "unit": "A"
      }
    },
    "weldingProcessTypes": {
      "type": "Property",
      "value": [
        "MIG",
        "MAG"
      ]
    },
    "materialCode": {
      "type": "Property",
      "value": "1700000103"
    }
  },
  {
    "@context": [
      "https://uri.etsi.org/ngsi-ld/v1/ngsi-ld-core-context.jsonld"
    ],
    "id": "urn:ngsi-ld:TwinObject:AutoEquipment:361-01404",
    "type": "TwinObject",
    "name": {
      "type": "Property",
      "value": "电弧焊接机"
    },
    "twinType": {
      "type": "Property",
      "value": "Constituent"
    },
    "subType": {
      "type": "Property",
      "value": "AutoEquipment"
    },
    "functionCategory": {
      "type": "Property",
      "value": "F1.2.1"
    },
    "deviceType": {
      "type": "Property",
      "value": "Welder"
    },
    "vendor": {
      "type": "Property",
      "value": "珠海市福尼斯焊接技术有限公司"
    },
    "model": {
      "type": "Property",
      "value": "TPS4000"
    },
    "serialNumber": {
      "type": "Property",
      "value": "21043925"
    },
    "assetNumber": {
      "type": "Property",
      "value": "361-01404"
    },
    "operationalStatus": {
      "type": "Property",
      "value": "在用"
    },
    "powerRating": {
      "type": "Property",
      "value": 14.0,
      "unitCode": "kW"
    },
    "weight": {
      "type": "Property",
      "value": 35.0,
      "unitCode": "kg"
    },
    "dimensions": {
      "type": "Property",
      "value": {
        "length_mm": 626.0,
        "width_mm": 287.0,
        "height_mm": 477.0
      }
    },
    "manufactureDate": {
      "type": "Property",
      "value": "2010-01-01"
    },
    "installationDate": {
      "type": "Property",
      "value": "2009-10-29"
    },
    "lastMaintenanceDate": {
      "type": "Property",
      "value": "2025-07-21"
    },
    "nextMaintenanceDate": {
      "type": "Property",
      "value": "2025-11-01"
    },
    "location": {
      "type": "Property",
      "value": "侧墙组焊工位 (TS36120201)"
    },
    "currentRange": {
      "type": "Property",
      "value": {
        "min": 30,
        "max": 300,
        "unit": "A"
      }
    },
    "weldingProcessTypes": {
      "type": "Property",
      "value": [
        "MIG",
        "MAG"
      ]
    },
    "materialCode": {
      "type": "Property",
      "value": "1700000103"
    }
  },
  {
    "@context": [
      "https://uri.etsi.org/ngsi-ld/v1/ngsi-ld-core-context.jsonld"
    ],
    "id": "urn:ngsi-ld:TwinObject:AutoEquipment:361-01309",
    "type": "TwinObject",
    "name": {
      "type": "Property",
      "value": "电弧焊接机"
    },
    "twinType": {
      "type": "Property",
      "value": "Constituent"
    },
    "subType": {
      "type": "Property",
      "value": "AutoEquipment"
    },
    "functionCategory": {
      "type": "Property",
      "value": "F1.2.1"
    },
    "deviceType": {
      "type": "Property",
      "value": "Welder"
    },
    "vendor": {
      "type": "Property",
      "value": "珠海市福尼斯焊接技术有限公司"
    },
    "model": {
      "type": "Property",
      "value": "TS/TPS4000"
    },
    "serialNumber": {
      "type": "Property",
      "value": "19061358"
    },
    "assetNumber": {
      "type": "Property",
      "value": "361-01309"
    },
    "operationalStatus": {
      "type": "Property",
      "value": "在用"
    },
    "powerRating": {
      "type": "Property",
      "value": 14.0,
      "unitCode": "kW"
    },
    "weight": {
      "type": "Property",
      "value": 3502.0,
      "unitCode": "kg"
    },
    "dimensions": {
      "type": "Property",
      "value": {
        "length_mm": 625.0,
        "width_mm": 290.0,
        "height_mm": 475.0
      }
    },
    "manufactureDate": {
      "type": "Property",
      "value": "2008-02-01"
    },
    "installationDate": {
      "type": "Property",
      "value": "2007-12-26"
    },
    "lastMaintenanceDate": {
      "type": "Property",
      "value": "2025-10-09"
    },
    "nextMaintenanceDate": {
      "type": "Property",
      "value": "2026-02-08"
    },
    "location": {
      "type": "Property",
      "value": "侧墙组焊工位 (TS36120201)"
    },
    "currentRange": {
      "type": "Property",
      "value": {
        "min": 30,
        "max": 300,
        "unit": "A"
      }
    },
    "weldingProcessTypes": {
      "type": "Property",
      "value": [
        "MIG",
        "MAG"
      ]
    },
    "materialCode": {
      "type": "Property",
      "value": "1700000105"
    }
  },
  {
    "@context": [
      "https://uri.etsi.org/ngsi-ld/v1/ngsi-ld-core-context.jsonld"
    ],
    "id": "urn:ngsi-ld:TwinObject:AutoEquipment:411-00219",
    "type": "TwinObject",
    "name": {
      "type": "Property",
      "value": "双梁桥式起重机"
    },
    "twinType": {
      "type": "Property",
      "value": "Constituent"
    },
    "subType": {
      "type": "Property",
      "value": "AutoEquipment"
    },
    "functionCategory": {
      "type": "Property",
      "value": "F1.2.1"
    },
    "deviceType": {
      "type": "Property",
      "value": "Other"
    },
    "vendor": {
      "type": "Property",
      "value": "大连铁道学院起重机厂"
    },
    "model": {
      "type": "Property",
      "value": "10T*28.5M"
    },
    "serialNumber": {
      "type": "Property",
      "value": "T0750007-3"
    },
    "assetNumber": {
      "type": "Property",
      "value": "411-00219"
    },
    "operationalStatus": {
      "type": "Property",
      "value": "在用"
    },
    "powerRating": {
      "type": "Property",
      "value": 40.0,
      "unitCode": "kW"
    },
    "weight": {
      "type": "Property",
      "value": 17560.0,
      "unitCode": "kg"
    },
    "dimensions": {
      "type": "Property",
      "value": {
        "length_mm": 28500.0,
        "width_mm": 5250.0,
        "height_mm": 1200.0
      }
    },
    "manufactureDate": {
      "type": "Property",
      "value": "2007-03-01"
    },
    "installationDate": {
      "type": "Property",
      "value": "2007-09-30"
    },
    "lastMaintenanceDate": {
      "type": "Property",
      "value": "2025-07-07"
    },
    "nextMaintenanceDate": {
      "type": "Property",
      "value": "2025-11-01"
    },
    "location": {
      "type": "Property",
      "value": "动车侧墙辅生产线 (TS361202)"
    },
    "materialCode": {
      "type": "Property",
      "value": "1700000152"
    }
  },
  {
    "@context": [
      "https://uri.etsi.org/ngsi-ld/v1/ngsi-ld-core-context.jsonld"
    ],
    "id": "urn:ngsi-ld:TwinObject:AutoEquipment:411-00220",
    "type": "TwinObject",
    "name": {
      "type": "Property",
      "value": "双梁桥式起重机"
    },
    "twinType": {
      "type": "Property",
      "value": "Constituent"
    },
    "subType": {
      "type": "Property",
      "value": "AutoEquipment"
    },
    "functionCategory": {
      "type": "Property",
      "value": "F1.2.1"
    },
    "deviceType": {
      "type": "Property",
      "value": "Other"
    },
    "vendor": {
      "type": "Property",
      "value": "大连铁道学院起重机厂"
    },
    "model": {
      "type": "Property",
      "value": "10T*28.5M"
    },
    "serialNumber": {
      "type": "Property",
      "value": "T0750007-4"
    },
    "assetNumber": {
      "type": "Property",
      "value": "411-00220"
    },
    "operationalStatus": {
      "type": "Property",
      "value": "在用"
    },
    "powerRating": {
      "type": "Property",
      "value": 40.0,
      "unitCode": "kW"
    },
    "weight": {
      "type": "Property",
      "value": 17560.0,
      "unitCode": "kg"
    },
    "dimensions": {
      "type": "Property",
      "value": {
        "length_mm": 28500.0,
        "width_mm": 5250.0,
        "height_mm": 1200.0
      }
    },
    "manufactureDate": {
      "type": "Property",
      "value": "2007-03-01"
    },
    "installationDate": {
      "type": "Property",
      "value": "2007-09-30"
    },
    "lastMaintenanceDate": {
      "type": "Property",
      "value": "2025-07-08"
    },
    "nextMaintenanceDate": {
      "type": "Property",
      "value": "2025-11-01"
    },
    "location": {
      "type": "Property",
      "value": "动车侧墙辅生产线 (TS361202)"
    },
    "materialCode": {
      "type": "Property",
      "value": "1700000152"
    }
  },
  {
    "@context": [
      "https://uri.etsi.org/ngsi-ld/v1/ngsi-ld-core-context.jsonld"
    ],
    "id": "urn:ngsi-ld:TwinObject:AutoEquipment:411-122",
    "type": "TwinObject",
    "name": {
      "type": "Property",
      "value": "双梁桥式起重机"
    },
    "twinType": {
      "type": "Property",
      "value": "Constituent"
    },
    "subType": {
      "type": "Property",
      "value": "AutoEquipment"
    },
    "functionCategory": {
      "type": "Property",
      "value": "F1.2.1"
    },
    "deviceType": {
      "type": "Property",
      "value": "Other"
    },
    "vendor": {
      "type": "Property",
      "value": "北京起重设备厂（科尼天车)"
    },
    "model": {
      "type": "Property",
      "value": "CXTD-101*28.5M"
    },
    "serialNumber": {
      "type": "Property",
      "value": "95449"
    },
    "assetNumber": {
      "type": "Property",
      "value": "411-122"
    },
    "operationalStatus": {
      "type": "Property",
      "value": "在用"
    },
    "powerRating": {
      "type": "Property",
      "value": 40.0,
      "unitCode": "kW"
    },
    "weight": {
      "type": "Property",
      "value": 1922.0,
      "unitCode": "kg"
    },
    "dimensions": {
      "type": "Property",
      "value": {
        "length_mm": 28770.0,
        "width_mm": 5010.0,
        "height_mm": 1200.0
      }
    },
    "manufactureDate": {
      "type": "Property",
      "value": "2004-03-01"
    },
    "installationDate": {
      "type": "Property",
      "value": "2003-04-28"
    },
    "lastMaintenanceDate": {
      "type": "Property",
      "value": "2025-07-11"
    },
    "nextMaintenanceDate": {
      "type": "Property",
      "value": "2025-11-01"
    },
    "location": {
      "type": "Property",
      "value": "动车侧墙辅生产线 (TS361202)"
    },
    "materialCode": {
      "type": "Property",
      "value": "1700000155"
    }
  },
  {
    "@context": [
      "https://uri.etsi.org/ngsi-ld/v1/ngsi-ld-core-context.jsonld"
    ],
    "id": "urn:ngsi-ld:TwinObject:AutoEquipment:411-123",
    "type": "TwinObject",
    "name": {
      "type": "Property",
      "value": "双梁桥式起重机"
    },
    "twinType": {
      "type": "Property",
      "value": "Constituent"
    },
    "subType": {
      "type": "Property",
      "value": "AutoEquipment"
    },
    "functionCategory": {
      "type": "Property",
      "value": "F1.2.1"
    },
    "deviceType": {
      "type": "Property",
      "value": "Other"
    },
    "vendor": {
      "type": "Property",
      "value": "北京起重设备厂（科尼天车)"
    },
    "model": {
      "type": "Property",
      "value": "CXTD-101*28.5M"
    },
    "serialNumber": {
      "type": "Property",
      "value": "37903"
    },
    "assetNumber": {
      "type": "Property",
      "value": "411-123"
    },
    "operationalStatus": {
      "type": "Property",
      "value": "在用"
    },
    "powerRating": {
      "type": "Property",
      "value": 40.0,
      "unitCode": "kW"
    },
    "weight": {
      "type": "Property",
      "value": 1922.0,
      "unitCode": "kg"
    },
    "dimensions": {
      "type": "Property",
      "value": {
        "length_mm": 28770.0,
        "width_mm": 5010.0,
        "height_mm": 1200.0
      }
    },
    "manufactureDate": {
      "type": "Property",
      "value": "2004-03-01"
    },
    "installationDate": {
      "type": "Property",
      "value": "2003-04-28"
    },
    "lastMaintenanceDate": {
      "type": "Property",
      "value": "2025-07-11"
    },
    "nextMaintenanceDate": {
      "type": "Property",
      "value": "2025-11-01"
    },
    "location": {
      "type": "Property",
      "value": "动车侧墙辅生产线 (TS361202)"
    },
    "materialCode": {
      "type": "Property",
      "value": "1700000155"
    }
  },
  {
    "@context": [
      "https://uri.etsi.org/ngsi-ld/v1/ngsi-ld-core-context.jsonld"
    ],
    "id": "urn:ngsi-ld:TwinObject:AutoEquipment:411-124",
    "type": "TwinObject",
    "name": {
      "type": "Property",
      "value": "双梁桥式起重机"
    },
    "twinType": {
      "type": "Property",
      "value": "Constituent"
    },
    "subType": {
      "type": "Property",
      "value": "AutoEquipment"
    },
    "functionCategory": {
      "type": "Property",
      "value": "F1.2.1"
    },
    "deviceType": {
      "type": "Property",
      "value": "Other"
    },
    "vendor": {
      "type": "Property",
      "value": "北京起重设备厂（科尼天车)"
    },
    "model": {
      "type": "Property",
      "value": "CXTD-101*28.5M"
    },
    "serialNumber": {
      "type": "Property",
      "value": "36665"
    },
    "assetNumber": {
      "type": "Property",
      "value": "411-124"
    },
    "operationalStatus": {
      "type": "Property",
      "value": "在用"
    },
    "powerRating": {
      "type": "Property",
      "value": 40.0,
      "unitCode": "kW"
    },
    "weight": {
      "type": "Property",
      "value": 1922.0,
      "unitCode": "kg"
    },
    "dimensions": {
      "type": "Property",
      "value": {
        "length_mm": 28770.0,
        "width_mm": 5010.0,
        "height_mm": 1200.0
      }
    },
    "manufactureDate": {
      "type": "Property",
      "value": "2004-03-01"
    },
    "installationDate": {
      "type": "Property",
      "value": "2003-04-28"
    },
    "lastMaintenanceDate": {
      "type": "Property",
      "value": "2025-07-07"
    },
    "nextMaintenanceDate": {
      "type": "Property",
      "value": "2025-11-01"
    },
    "location": {
      "type": "Property",
      "value": "动车侧墙辅生产线 (TS361202)"
    },
    "materialCode": {
      "type": "Property",
      "value": "1700000155"
    }
  },
  {
    "@context": [
      "https://uri.etsi.org/ngsi-ld/v1/ngsi-ld-core-context.jsonld"
    ],
    "id": "urn:ngsi-ld:TwinObject:AutoEquipment:411-125",
    "type": "TwinObject",
    "name": {
      "type": "Property",
      "value": "双梁桥式起重机"
    },
    "twinType": {
      "type": "Property",
      "value": "Constituent"
    },
    "subType": {
      "type": "Property",
      "value": "AutoEquipment"
    },
    "functionCategory": {
      "type": "Property",
      "value": "F1.2.1"
    },
    "deviceType": {
      "type": "Property",
      "value": "Other"
    },
    "vendor": {
      "type": "Property",
      "value": "北京起重设备厂（科尼天车)"
    },
    "model": {
      "type": "Property",
      "value": "CXTD101*28.5M"
    },
    "serialNumber": {
      "type": "Property",
      "value": "60293"
    },
    "assetNumber": {
      "type": "Property",
      "value": "411-125"
    },
    "operationalStatus": {
      "type": "Property",
      "value": "在用"
    },
    "powerRating": {
      "type": "Property",
      "value": 40.0,
      "unitCode": "kW"
    },
    "weight": {
      "type": "Property",
      "value": 1922.0,
      "unitCode": "kg"
    },
    "dimensions": {
      "type": "Property",
      "value": {
        "length_mm": 28770.0,
        "width_mm": 5010.0,
        "height_mm": 1200.0
      }
    },
    "manufactureDate": {
      "type": "Property",
      "value": "2004-03-01"
    },
    "installationDate": {
      "type": "Property",
      "value": "2003-04-28"
    },
    "lastMaintenanceDate": {
      "type": "Property",
      "value": "2025-07-11"
    },
    "nextMaintenanceDate": {
      "type": "Property",
      "value": "2025-11-01"
    },
    "location": {
      "type": "Property",
      "value": "动车侧墙辅生产线 (TS361202)"
    },
    "materialCode": {
      "type": "Property",
      "value": "1700000155"
    }
  },
  {
    "@context": [
      "https://uri.etsi.org/ngsi-ld/v1/ngsi-ld-core-context.jsonld"
    ],
    "id": "urn:ngsi-ld:TwinObject:AutoEquipment:361-02201",
    "type": "TwinObject",
    "name": {
      "type": "Property",
      "value": "电弧焊接机"
    },
    "twinType": {
      "type": "Property",
      "value": "Constituent"
    },
    "subType": {
      "type": "Property",
      "value": "AutoEquipment"
    },
    "functionCategory": {
      "type": "Property",
      "value": "F1.2.1"
    },
    "deviceType": {
      "type": "Property",
      "value": "Welder"
    },
    "vendor": {
      "type": "Property",
      "value": "奥地利利伏能焊接技术国际有限公司"
    },
    "model": {
      "type": "Property",
      "value": "TPS400i"
    },
    "serialNumber": {
      "type": "Property",
      "value": "35386772"
    },
    "assetNumber": {
      "type": "Property",
      "value": "361-02201"
    },
    "operationalStatus": {
      "type": "Property",
      "value": "在用"
    },
    "powerRating": {
      "type": "Property",
      "value": 13.6,
      "unitCode": "kW"
    },
    "weight": {
      "type": "Property",
      "value": 36.5,
      "unitCode": "kg"
    },
    "dimensions": {
      "type": "Property",
      "value": {
        "length_mm": 706.0,
        "width_mm": 300.0,
        "height_mm": 510.0
      }
    },
    "manufactureDate": {
      "type": "Property",
      "value": "2025-05-01"
    },
    "installationDate": {
      "type": "Property",
      "value": "2025-07-02"
    },
    "lastMaintenanceDate": {
      "type": "Property",
      "value": "2025-07-21"
    },
    "nextMaintenanceDate": {
      "type": "Property",
      "value": "2025-11-01"
    },
    "location": {
      "type": "Property",
      "value": "动车侧墙辅生产线 (TS361202)"
    },
    "currentRange": {
      "type": "Property",
      "value": {
        "min": 30,
        "max": 300,
        "unit": "A"
      }
    },
    "weldingProcessTypes": {
      "type": "Property",
      "value": [
        "MIG",
        "MAG"
      ]
    },
    "materialCode": {
      "type": "Property",
      "value": "1700000103"
    }
  },
  {
    "@context": [
      "https://uri.etsi.org/ngsi-ld/v1/ngsi-ld-core-context.jsonld"
    ],
    "id": "urn:ngsi-ld:TwinObject:AutoEquipment:361-02198",
    "type": "TwinObject",
    "name": {
      "type": "Property",
      "value": "电弧焊接机"
    },
    "twinType": {
      "type": "Property",
      "value": "Constituent"
    },
    "subType": {
      "type": "Property",
      "value": "AutoEquipment"
    },
    "functionCategory": {
      "type": "Property",
      "value": "F1.2.1"
    },
    "deviceType": {
      "type": "Property",
      "value": "Welder"
    },
    "vendor": {
      "type": "Property",
      "value": "奥地利利伏能焊接技术国际有限公司"
    },
    "model": {
      "type": "Property",
      "value": "TPS400i"
    },
    "serialNumber": {
      "type": "Property",
      "value": "35386760"
    },
    "assetNumber": {
      "type": "Property",
      "value": "361-02198"
    },
    "operationalStatus": {
      "type": "Property",
      "value": "在用"
    },
    "powerRating": {
      "type": "Property",
      "value": 13.6,
      "unitCode": "kW"
    },
    "weight": {
      "type": "Property",
      "value": 36.5,
      "unitCode": "kg"
    },
    "dimensions": {
      "type": "Property",
      "value": {
        "length_mm": 706.0,
        "width_mm": 300.0,
        "height_mm": 510.0
      }
    },
    "manufactureDate": {
      "type": "Property",
      "value": "2025-05-01"
    },
    "installationDate": {
      "type": "Property",
      "value": "2025-07-02"
    },
    "lastMaintenanceDate": {
      "type": "Property",
      "value": "2025-07-18"
    },
    "nextMaintenanceDate": {
      "type": "Property",
      "value": "2025-11-01"
    },
    "location": {
      "type": "Property",
      "value": "动车侧墙辅生产线 (TS361202)"
    },
    "currentRange": {
      "type": "Property",
      "value": {
        "min": 30,
        "max": 300,
        "unit": "A"
      }
    },
    "weldingProcessTypes": {
      "type": "Property",
      "value": [
        "MIG",
        "MAG"
      ]
    },
    "materialCode": {
      "type": "Property",
      "value": "1700000103"
    }
  },
  {
    "@context": [
      "https://uri.etsi.org/ngsi-ld/v1/ngsi-ld-core-context.jsonld"
    ],
    "id": "urn:ngsi-ld:TwinObject:AutoEquipment:361-01127",
    "type": "TwinObject",
    "name": {
      "type": "Property",
      "value": "电弧焊接机"
    },
    "twinType": {
      "type": "Property",
      "value": "Constituent"
    },
    "subType": {
      "type": "Property",
      "value": "AutoEquipment"
    },
    "functionCategory": {
      "type": "Property",
      "value": "F1.2.1"
    },
    "deviceType": {
      "type": "Property",
      "value": "Welder"
    },
    "vendor": {
      "type": "Property",
      "value": "2025.07.02"
    },
    "model": {
      "type": "Property",
      "value": "TPS400i"
    },
    "serialNumber": {
      "type": "Property",
      "value": "35358322"
    },
    "assetNumber": {
      "type": "Property",
      "value": "361-01127"
    },
    "operationalStatus": {
      "type": "Property",
      "value": "在用"
    },
    "powerRating": {
      "type": "Property",
      "value": 13.6,
      "unitCode": "kW"
    },
    "weight": {
      "type": "Property",
      "value": 36.5,
      "unitCode": "kg"
    },
    "dimensions": {
      "type": "Property",
      "value": {
        "length_mm": 706.0,
        "width_mm": 300.0,
        "height_mm": 510.0
      }
    },
    "manufactureDate": {
      "type": "Property",
      "value": "2025-05-01"
    },
    "installationDate": {
      "type": "Property",
      "value": "2025-07-02"
    },
    "lastMaintenanceDate": {
      "type": "Property",
      "value": "2025-07-21"
    },
    "nextMaintenanceDate": {
      "type": "Property",
      "value": "2025-11-01"
    },
    "location": {
      "type": "Property",
      "value": "动车侧墙辅生产线 (TS361202)"
    },
    "currentRange": {
      "type": "Property",
      "value": {
        "min": 30,
        "max": 300,
        "unit": "A"
      }
    },
    "weldingProcessTypes": {
      "type": "Property",
      "value": [
        "MIG",
        "MAG"
      ]
    },
    "materialCode": {
      "type": "Property",
      "value": "1700000103"
    }
  },
  {
    "@context": [
      "https://uri.etsi.org/ngsi-ld/v1/ngsi-ld-core-context.jsonld"
    ],
    "id": "urn:ngsi-ld:TwinObject:AutoEquipment:361-01163",
    "type": "TwinObject",
    "name": {
      "type": "Property",
      "value": "电弧焊接机"
    },
    "twinType": {
      "type": "Property",
      "value": "Constituent"
    },
    "subType": {
      "type": "Property",
      "value": "AutoEquipment"
    },
    "functionCategory": {
      "type": "Property",
      "value": "F1.2.1"
    },
    "deviceType": {
      "type": "Property",
      "value": "Welder"
    },
    "vendor": {
      "type": "Property",
      "value": "珠海市福尼斯焊接技术有限公司"
    },
    "model": {
      "type": "Property",
      "value": "TPS5000"
    },
    "serialNumber": {
      "type": "Property",
      "value": "18140118"
    },
    "assetNumber": {
      "type": "Property",
      "value": "361-01163"
    },
    "operationalStatus": {
      "type": "Property",
      "value": "在用"
    },
    "powerRating": {
      "type": "Property",
      "value": 14.0,
      "unitCode": "kW"
    },
    "weight": {
      "type": "Property",
      "value": 35.0,
      "unitCode": "kg"
    },
    "dimensions": {
      "type": "Property",
      "value": {
        "length_mm": 620.0,
        "width_mm": 300.0,
        "height_mm": 700.0
      }
    },
    "manufactureDate": {
      "type": "Property",
      "value": "2007-05-01"
    },
    "installationDate": {
      "type": "Property",
      "value": "2006-09-30"
    },
    "lastMaintenanceDate": {
      "type": "Property",
      "value": "2025-10-20"
    },
    "nextMaintenanceDate": {
      "type": "Property",
      "value": "2026-02-20"
    },
    "location": {
      "type": "Property",
      "value": "侧墙附件组焊工位 (TS36120204)"
    },
    "currentRange": {
      "type": "Property",
      "value": {
        "min": 50,
        "max": 500,
        "unit": "A"
      }
    },
    "weldingProcessTypes": {
      "type": "Property",
      "value": [
        "MIG",
        "MAG"
      ]
    },
    "materialCode": {
      "type": "Property",
      "value": "1700000104"
    }
  },
  {
    "@context": [
      "https://uri.etsi.org/ngsi-ld/v1/ngsi-ld-core-context.jsonld"
    ],
    "id": "urn:ngsi-ld:TwinObject:AutoEquipment:361-1075",
    "type": "TwinObject",
    "name": {
      "type": "Property",
      "value": "电弧焊接机"
    },
    "twinType": {
      "type": "Property",
      "value": "Constituent"
    },
    "subType": {
      "type": "Property",
      "value": "AutoEquipment"
    },
    "functionCategory": {
      "type": "Property",
      "value": "F1.2.1"
    },
    "deviceType": {
      "type": "Property",
      "value": "Welder"
    },
    "vendor": {
      "type": "Property",
      "value": "唐山松下产业机器有限公司"
    },
    "model": {
      "type": "Property",
      "value": "YC-500WX4HNE"
    },
    "serialNumber": {
      "type": "Property",
      "value": "20807S0010"
    },
    "assetNumber": {
      "type": "Property",
      "value": "361-1075"
    },
    "operationalStatus": {
      "type": "Property",
      "value": "在用"
    },
    "powerRating": {
      "type": "Property",
      "value": 14.0,
      "unitCode": "kW"
    },
    "weight": {
      "type": "Property",
      "value": 3502.0,
      "unitCode": "kg"
    },
    "dimensions": {
      "type": "Property",
      "value": {
        "length_mm": 625.0,
        "width_mm": 290.0,
        "height_mm": 475.0
      }
    },
    "manufactureDate": {
      "type": "Property",
      "value": "2007-04-01"
    },
    "installationDate": {
      "type": "Property",
      "value": "2006-05-14"
    },
    "lastMaintenanceDate": {
      "type": "Property",
      "value": "2025-08-06"
    },
    "nextMaintenanceDate": {
      "type": "Property",
      "value": "2025-12-06"
    },
    "location": {
      "type": "Property",
      "value": "侧墙附件组焊工位 (TS36120204)"
    },
    "weldingProcessTypes": {
      "type": "Property",
      "value": [
        "MIG",
        "MAG"
      ]
    },
    "materialCode": {
      "type": "Property",
      "value": "1700000107"
    }
  },
  {
    "@context": [
      "https://uri.etsi.org/ngsi-ld/v1/ngsi-ld-core-context.jsonld"
    ],
    "id": "urn:ngsi-ld:TwinObject:AutoEquipment:361-01189",
    "type": "TwinObject",
    "name": {
      "type": "Property",
      "value": "电弧焊接机"
    },
    "twinType": {
      "type": "Property",
      "value": "Constituent"
    },
    "subType": {
      "type": "Property",
      "value": "AutoEquipment"
    },
    "functionCategory": {
      "type": "Property",
      "value": "F1.2.1"
    },
    "deviceType": {
      "type": "Property",
      "value": "Welder"
    },
    "vendor": {
      "type": "Property",
      "value": "珠海市福尼斯焊接技术有限公司"
    },
    "model": {
      "type": "Property",
      "value": "TPS4000"
    },
    "serialNumber": {
      "type": "Property",
      "value": "18130447"
    },
    "assetNumber": {
      "type": "Property",
      "value": "361-01189"
    },
    "operationalStatus": {
      "type": "Property",
      "value": "在用"
    },
    "powerRating": {
      "type": "Property",
      "value": 14.0,
      "unitCode": "kW"
    },
    "weight": {
      "type": "Property",
      "value": 35.0,
      "unitCode": "kg"
    },
    "dimensions": {
      "type": "Property",
      "value": {
        "length_mm": 620.0,
        "width_mm": 300.0,
        "height_mm": 700.0
      }
    },
    "manufactureDate": {
      "type": "Property",
      "value": "2007-05-01"
    },
    "installationDate": {
      "type": "Property",
      "value": "2006-01-27"
    },
    "lastMaintenanceDate": {
      "type": "Property",
      "value": "2025-10-14"
    },
    "nextMaintenanceDate": {
      "type": "Property",
      "value": "2026-02-13"
    },
    "location": {
      "type": "Property",
      "value": "侧墙附件组焊工位 (TS36120204)"
    },
    "currentRange": {
      "type": "Property",
      "value": {
        "min": 30,
        "max": 300,
        "unit": "A"
      }
    },
    "weldingProcessTypes": {
      "type": "Property",
      "value": [
        "MIG",
        "MAG"
      ]
    },
    "materialCode": {
      "type": "Property",
      "value": "1700000103"
    }
  },
  {
    "@context": [
      "https://uri.etsi.org/ngsi-ld/v1/ngsi-ld-core-context.jsonld"
    ],
    "id": "urn:ngsi-ld:TwinObject:AutoEquipment:361-1099",
    "type": "TwinObject",
    "name": {
      "type": "Property",
      "value": "电弧焊接机"
    },
    "twinType": {
      "type": "Property",
      "value": "Constituent"
    },
    "subType": {
      "type": "Property",
      "value": "AutoEquipment"
    },
    "functionCategory": {
      "type": "Property",
      "value": "F1.2.1"
    },
    "deviceType": {
      "type": "Property",
      "value": "Welder"
    },
    "vendor": {
      "type": "Property",
      "value": "珠海市福尼斯焊接技术有限公司"
    },
    "model": {
      "type": "Property",
      "value": "TPS4000"
    },
    "serialNumber": {
      "type": "Property",
      "value": "18110556"
    },
    "assetNumber": {
      "type": "Property",
      "value": "361-1099"
    },
    "operationalStatus": {
      "type": "Property",
      "value": "在用"
    },
    "powerRating": {
      "type": "Property",
      "value": 14.0,
      "unitCode": "kW"
    },
    "weight": {
      "type": "Property",
      "value": 3502.0,
      "unitCode": "kg"
    },
    "dimensions": {
      "type": "Property",
      "value": {
        "length_mm": 625.0,
        "width_mm": 290.0,
        "height_mm": 475.0
      }
    },
    "manufactureDate": {
      "type": "Property",
      "value": "2007-04-01"
    },
    "installationDate": {
      "type": "Property",
      "value": "2006-08-31"
    },
    "lastMaintenanceDate": {
      "type": "Property",
      "value": "2025-09-15"
    },
    "nextMaintenanceDate": {
      "type": "Property",
      "value": "2026-01-15"
    },
    "location": {
      "type": "Property",
      "value": "侧墙附件组焊工位 (TS36120204)"
    },
    "currentRange": {
      "type": "Property",
      "value": {
        "min": 30,
        "max": 300,
        "unit": "A"
      }
    },
    "weldingProcessTypes": {
      "type": "Property",
      "value": [
        "MIG",
        "MAG"
      ]
    },
    "materialCode": {
      "type": "Property",
      "value": "1700000103"
    }
  },
  {
    "@context": [
      "https://uri.etsi.org/ngsi-ld/v1/ngsi-ld-core-context.jsonld"
    ],
    "id": "urn:ngsi-ld:TwinObject:AutoEquipment:361-01402",
    "type": "TwinObject",
    "name": {
      "type": "Property",
      "value": "电弧焊接机"
    },
    "twinType": {
      "type": "Property",
      "value": "Constituent"
    },
    "subType": {
      "type": "Property",
      "value": "AutoEquipment"
    },
    "functionCategory": {
      "type": "Property",
      "value": "F1.2.1"
    },
    "deviceType": {
      "type": "Property",
      "value": "Welder"
    },
    "vendor": {
      "type": "Property",
      "value": "珠海市福尼斯焊接技术有限公司"
    },
    "model": {
      "type": "Property",
      "value": "TPS4000"
    },
    "serialNumber": {
      "type": "Property",
      "value": "21043927"
    },
    "assetNumber": {
      "type": "Property",
      "value": "361-01402"
    },
    "operationalStatus": {
      "type": "Property",
      "value": "在用"
    },
    "powerRating": {
      "type": "Property",
      "value": 14.0,
      "unitCode": "kW"
    },
    "weight": {
      "type": "Property",
      "value": 35.0,
      "unitCode": "kg"
    },
    "dimensions": {
      "type": "Property",
      "value": {
        "length_mm": 626.0,
        "width_mm": 287.0,
        "height_mm": 477.0
      }
    },
    "manufactureDate": {
      "type": "Property",
      "value": "2010-01-01"
    },
    "installationDate": {
      "type": "Property",
      "value": "2009-10-29"
    },
    "lastMaintenanceDate": {
      "type": "Property",
      "value": "2025-09-11"
    },
    "nextMaintenanceDate": {
      "type": "Property",
      "value": "2026-01-11"
    },
    "location": {
      "type": "Property",
      "value": "侧墙附件组焊工位 (TS36120204)"
    },
    "currentRange": {
      "type": "Property",
      "value": {
        "min": 30,
        "max": 300,
        "unit": "A"
      }
    },
    "weldingProcessTypes": {
      "type": "Property",
      "value": [
        "MIG",
        "MAG"
      ]
    },
    "materialCode": {
      "type": "Property",
      "value": "1700000103"
    }
  },
  {
    "@context": [
      "https://uri.etsi.org/ngsi-ld/v1/ngsi-ld-core-context.jsonld"
    ],
    "id": "urn:ngsi-ld:TwinObject:AutoEquipment:999-00690",
    "type": "TwinObject",
    "name": {
      "type": "Property",
      "value": "侧墙自动化打磨设备"
    },
    "twinType": {
      "type": "Property",
      "value": "Constituent"
    },
    "subType": {
      "type": "Property",
      "value": "AutoEquipment"
    },
    "functionCategory": {
      "type": "Property",
      "value": "F1.2.1"
    },
    "deviceType": {
      "type": "Property",
      "value": "Other"
    },
    "vendor": {
      "type": "Property",
      "value": "天津智通信息系统集成有限公司"
    },
    "model": {
      "type": "Property",
      "value": "非标"
    },
    "assetNumber": {
      "type": "Property",
      "value": "999-00690"
    },
    "operationalStatus": {
      "type": "Property",
      "value": "在用"
    },
    "weight": {
      "type": "Property",
      "value": 9500.0,
      "unitCode": "kg"
    },
    "dimensions": {
      "type": "Property",
      "value": {
        "length_mm": 34900.0,
        "width_mm": 6100.0,
        "height_mm": 3100.0
      }
    },
    "manufactureDate": {
      "type": "Property",
      "value": "2019-06-01"
    },
    "installationDate": {
      "type": "Property",
      "value": "2019-06-25"
    },
    "lastMaintenanceDate": {
      "type": "Property",
      "value": "2025-10-20"
    },
    "nextMaintenanceDate": {
      "type": "Property",
      "value": "2026-01-20"
    },
    "location": {
      "type": "Property",
      "value": "侧墙附件组焊工位 (TS36120204)"
    },
    "materialCode": {
      "type": "Property",
      "value": "1700001351"
    }
  },
  {
    "@context": [
      "https://uri.etsi.org/ngsi-ld/v1/ngsi-ld-core-context.jsonld"
    ],
    "id": "urn:ngsi-ld:TwinObject:AutoEquipment:361-01295",
    "type": "TwinObject",
    "name": {
      "type": "Property",
      "value": "电弧焊接机"
    },
    "twinType": {
      "type": "Property",
      "value": "Constituent"
    },
    "subType": {
      "type": "Property",
      "value": "AutoEquipment"
    },
    "functionCategory": {
      "type": "Property",
      "value": "F1.2.1"
    },
    "deviceType": {
      "type": "Property",
      "value": "Welder"
    },
    "vendor": {
      "type": "Property",
      "value": "珠海市福尼斯焊接技术有限公司"
    },
    "model": {
      "type": "Property",
      "value": "TS/TPS4000"
    },
    "serialNumber": {
      "type": "Property",
      "value": "17342925"
    },
    "assetNumber": {
      "type": "Property",
      "value": "361-01295"
    },
    "operationalStatus": {
      "type": "Property",
      "value": "在用"
    },
    "powerRating": {
      "type": "Property",
      "value": 14.0,
      "unitCode": "kW"
    },
    "weight": {
      "type": "Property",
      "value": 3502.0,
      "unitCode": "kg"
    },
    "dimensions": {
      "type": "Property",
      "value": {
        "length_mm": 625.0,
        "width_mm": 290.0,
        "height_mm": 475.0
      }
    },
    "manufactureDate": {
      "type": "Property",
      "value": "2008-02-01"
    },
    "installationDate": {
      "type": "Property",
      "value": "2007-12-26"
    },
    "lastMaintenanceDate": {
      "type": "Property",
      "value": "2025-07-07"
    },
    "nextMaintenanceDate": {
      "type": "Property",
      "value": "2025-10-25"
    },
    "location": {
      "type": "Property",
      "value": "侧墙附件组焊工位 (TS36120204)"
    },
    "currentRange": {
      "type": "Property",
      "value": {
        "min": 30,
        "max": 300,
        "unit": "A"
      }
    },
    "weldingProcessTypes": {
      "type": "Property",
      "value": [
        "MIG",
        "MAG"
      ]
    },
    "materialCode": {
      "type": "Property",
      "value": "1700000105"
    }
  },
  {
    "@context": [
      "https://uri.etsi.org/ngsi-ld/v1/ngsi-ld-core-context.jsonld"
    ],
    "id": "urn:ngsi-ld:TwinObject:AutoEquipment:046-4",
    "type": "TwinObject",
    "name": {
      "type": "Property",
      "value": "加工中心"
    },
    "twinType": {
      "type": "Property",
      "value": "Constituent"
    },
    "subType": {
      "type": "Property",
      "value": "AutoEquipment"
    },
    "functionCategory": {
      "type": "Property",
      "value": "F1.2.1"
    },
    "deviceType": {
      "type": "Property",
      "value": "CNC"
    },
    "vendor": {
      "type": "Property",
      "value": "德国FOOKE公司"
    },
    "model": {
      "type": "Property",
      "value": "ENDURA8LB"
    },
    "serialNumber": {
      "type": "Property",
      "value": "19400"
    },
    "assetNumber": {
      "type": "Property",
      "value": "046-4"
    },
    "operationalStatus": {
      "type": "Property",
      "value": "在用"
    },
    "powerRating": {
      "type": "Property",
      "value": 100.0,
      "unitCode": "kW"
    },
    "weight": {
      "type": "Property",
      "value": 160000.0,
      "unitCode": "kg"
    },
    "dimensions": {
      "type": "Property",
      "value": {
        "length_mm": 61600.0,
        "width_mm": 5500.0,
        "height_mm": 6828.0
      }
    },
    "manufactureDate": {
      "type": "Property",
      "value": "2004-01-01"
    },
    "installationDate": {
      "type": "Property",
      "value": "2004-07-28"
    },
    "lastMaintenanceDate": {
      "type": "Property",
      "value": "2025-10-08"
    },
    "nextMaintenanceDate": {
      "type": "Property",
      "value": "2026-01-08"
    },
    "location": {
      "type": "Property",
      "value": "侧墙加工工位 (TS36120203)"
    },
    "axes": {
      "type": "Property",
      "value": 3,
      "unitCode": "axes"
    },
    "materialCode": {
      "type": "Property",
      "value": "1700000063"
    }
  },
  {
    "@context": [
      "https://uri.etsi.org/ngsi-ld/v1/ngsi-ld-core-context.jsonld"
    ],
    "id": "urn:ngsi-ld:TwinObject:AutoEquipment:999-00112",
    "type": "TwinObject",
    "name": {
      "type": "Property",
      "value": "隔音房"
    },
    "twinType": {
      "type": "Property",
      "value": "Constituent"
    },
    "subType": {
      "type": "Property",
      "value": "AutoEquipment"
    },
    "functionCategory": {
      "type": "Property",
      "value": "F1.2.1"
    },
    "deviceType": {
      "type": "Property",
      "value": "Other"
    },
    "vendor": {
      "type": "Property",
      "value": "长春市开得科贸有限公司"
    },
    "model": {
      "type": "Property",
      "value": "非标"
    },
    "serialNumber": {
      "type": "Property",
      "value": "CTDC0713"
    },
    "assetNumber": {
      "type": "Property",
      "value": "999-00112"
    },
    "operationalStatus": {
      "type": "Property",
      "value": "在用"
    },
    "powerRating": {
      "type": "Property",
      "value": 60.0,
      "unitCode": "kW"
    },
    "weight": {
      "type": "Property",
      "value": 60000.0,
      "unitCode": "kg"
    },
    "dimensions": {
      "type": "Property",
      "value": {
        "length_mm": 42000.0,
        "width_mm": 10900.0,
        "height_mm": 7500.0
      }
    },
    "manufactureDate": {
      "type": "Property",
      "value": "2008-01-01"
    },
    "installationDate": {
      "type": "Property",
      "value": "2007-09-30"
    },
    "lastMaintenanceDate": {
      "type": "Property",
      "value": "2025-10-09"
    },
    "nextMaintenanceDate": {
      "type": "Property",
      "value": "2026-02-09"
    },
    "location": {
      "type": "Property",
      "value": "侧墙加工工位 (TS36120203)"
    },
    "materialCode": {
      "type": "Property",
      "value": "1700000348"
    }
  },
  {
    "@context": [
      "https://uri.etsi.org/ngsi-ld/v1/ngsi-ld-core-context.jsonld"
    ],
    "id": "urn:ngsi-ld:TwinObject:AutoEquipment:999-00327",
    "type": "TwinObject",
    "name": {
      "type": "Property",
      "value": "隔音房"
    },
    "twinType": {
      "type": "Property",
      "value": "Constituent"
    },
    "subType": {
      "type": "Property",
      "value": "AutoEquipment"
    },
    "functionCategory": {
      "type": "Property",
      "value": "F1.2.1"
    },
    "deviceType": {
      "type": "Property",
      "value": "Other"
    },
    "vendor": {
      "type": "Property",
      "value": "长春市开得科贸有限公司"
    },
    "model": {
      "type": "Property",
      "value": "GYF01"
    },
    "serialNumber": {
      "type": "Property",
      "value": "CTDC0622"
    },
    "assetNumber": {
      "type": "Property",
      "value": "999-00327"
    },
    "operationalStatus": {
      "type": "Property",
      "value": "在用"
    },
    "powerRating": {
      "type": "Property",
      "value": 30.0,
      "unitCode": "kW"
    },
    "weight": {
      "type": "Property",
      "value": 60000.0,
      "unitCode": "kg"
    },
    "dimensions": {
      "type": "Property",
      "value": {
        "length_mm": 42700.0,
        "width_mm": 9000.0,
        "height_mm": 7500.0
      }
    },
    "manufactureDate": {
      "type": "Property",
      "value": "2007-01-01"
    },
    "installationDate": {
      "type": "Property",
      "value": "2007-04-30"
    },
    "lastMaintenanceDate": {
      "type": "Property",
      "value": "2025-10-09"
    },
    "nextMaintenanceDate": {
      "type": "Property",
      "value": "2026-02-09"
    },
    "location": {
      "type": "Property",
      "value": "侧墙加工工位 (TS36120203)"
    },
    "materialCode": {
      "type": "Property",
      "value": "1700000328"
    }
  },
  {
    "@context": [
      "https://uri.etsi.org/ngsi-ld/v1/ngsi-ld-core-context.jsonld"
    ],
    "id": "urn:ngsi-ld:TwinObject:AutoEquipment:046-00019",
    "type": "TwinObject",
    "name": {
      "type": "Property",
      "value": "加工中心"
    },
    "twinType": {
      "type": "Property",
      "value": "Constituent"
    },
    "subType": {
      "type": "Property",
      "value": "AutoEquipment"
    },
    "functionCategory": {
      "type": "Property",
      "value": "F1.2.1"
    },
    "deviceType": {
      "type": "Property",
      "value": "CNC"
    },
    "vendor": {
      "type": "Property",
      "value": "德国FOOKE公司"
    },
    "model": {
      "type": "Property",
      "value": "ENDURA 10LB"
    },
    "serialNumber": {
      "type": "Property",
      "value": "22480"
    },
    "assetNumber": {
      "type": "Property",
      "value": "046-00019"
    },
    "operationalStatus": {
      "type": "Property",
      "value": "在用"
    },
    "powerRating": {
      "type": "Property",
      "value": 100.0,
      "unitCode": "kW"
    },
    "weight": {
      "type": "Property",
      "value": 16000.0,
      "unitCode": "kg"
    },
    "dimensions": {
      "type": "Property",
      "value": {
        "length_mm": 76000.0,
        "width_mm": 9000.0,
        "height_mm": 6500.0
      }
    },
    "manufactureDate": {
      "type": "Property",
      "value": "2006-11-01"
    },
    "installationDate": {
      "type": "Property",
      "value": "2006-11-30"
    },
    "lastMaintenanceDate": {
      "type": "Property",
      "value": "2025-10-08"
    },
    "nextMaintenanceDate": {
      "type": "Property",
      "value": "2026-01-08"
    },
    "location": {
      "type": "Property",
      "value": "侧墙加工工位 (TS36120203)"
    },
    "axes": {
      "type": "Property",
      "value": 3,
      "unitCode": "axes"
    },
    "materialCode": {
      "type": "Property",
      "value": "1700000061"
    }
  }
]